README.rst
setup.cfg
setup.py
sockjs_flask/__init__.py
sockjs_flask/database.py
sockjs_flask/exceptions.py
sockjs_flask/handler.py
sockjs_flask/hdrs.py
sockjs_flask/protocol.py
sockjs_flask/route.py
sockjs_flask/server.py
sockjs_flask/session.py
sockjs_flask/subscription.py
sockjs_flask.egg-info/PKG-INFO
sockjs_flask.egg-info/SOURCES.txt
sockjs_flask.egg-info/dependency_links.txt
sockjs_flask.egg-info/requires.txt
sockjs_flask.egg-info/top_level.txt
sockjs_flask/gunicorn/__init__.py
sockjs_flask/gunicorn/workers.py
sockjs_flask/sessions/__init__.py
sockjs_flask/sessions/memory.py
sockjs_flask/sessions/redis.py
sockjs_flask/sessions/zeromq.py
sockjs_flask/transports/__init__.py
sockjs_flask/transports/base.py
sockjs_flask/transports/eventsource.py
sockjs_flask/transports/ihf.py
sockjs_flask/transports/jsonp.py
sockjs_flask/transports/rawwebsocket.py
sockjs_flask/transports/utils.py
sockjs_flask/transports/websocket.py
sockjs_flask/transports/xhr.py
sockjs_flask/transports/xhrsend.py
sockjs_flask/transports/xhrstreaming.py
tests/__init__.py
tests/test_route.py
tests/test_session.py