Metadata-Version: 1.1
Name: sockjs-flask
Version: 0.3
Summary: SockJs for Flask
Home-page: https://github.com/pycodi/sockjs-flask
Author: Kryuchkov Nikita
Author-email: pycodi@hotmail.com
License: UNKNOWN
Platform: UNKNOWN
Classifier: Intended Audience :: Developers
Classifier: Programming Language :: Python
Classifier: Programming Language :: Python :: 3
Classifier: Programming Language :: Python :: 3.4
Classifier: Programming Language :: Python :: 3.5
